django_namedtuples/__init__.py
django_namedtuples/queryset.py
django_namedtuples-2.0.0.dist-info/LICENSE
django_namedtuples-2.0.0.dist-info/METADATA
django_namedtuples-2.0.0.dist-info/WHEEL
django_namedtuples-2.0.0.dist-info/top_level.txt
django_namedtuples-2.0.0.dist-info/RECORD
